{
  "daily": {
    "date": "2026-06-16",
    "count": 7,
    "limit": 17
  },
  "stories": {
    "sandro_tonali_spurs_transfer": {
      "stage": 1,
      "player": "Sandro Tonali",
      "clubs": [
        "Spurs",
        "Spurs",
        "Man_City",
        "Arsenal"
      ],
      "type": "transfer",
      "status": "active",
      "sources": [
        "FabrizioRomano"
      ],
      "last_updated": "2026-06-16T03:46:34.455958+00:00"
    },
    "steve_nickson_newcastle_transfer": {
      "stage": 1,
      "player": "Steve Nickson",
      "clubs": [
        "Newcastle"
      ],
      "type": "transfer",
      "status": "active",
      "sources": [
        "David_Ornstein"
      ],
      "last_updated": "2026-06-16T03:47:35.598756+00:00"
    },
    "pierre_sage_crystal_palace_manager": {
      "stage": 1,
      "player": "Pierre Sage",
      "clubs": [
        "Crystal_Palace"
      ],
      "type": "manager",
      "status": "active",
      "sources": [
        "David_Ornstein"
      ],
      "last_updated": "2026-06-16T03:48:36.648275+00:00"
    },
    "marcus_rashford_man_utd_transfer": {
      "stage": 1,
      "player": "Marcus Rashford",
      "clubs": [
        "Man_Utd",
        "Man_Utd"
      ],
      "type": "transfer",
      "status": "active",
      "sources": [
        "FabrizioRomano"
      ],
      "last_updated": "2026-06-16T08:09:37.391785+00:00"
    }
  },
  "posted_ids": [
    "2066197024223928546",
    "2066614088319238237",
    "2066577035296985128",
    "2066694767677669467",
    "2066642303582716133",
    "2066641595391189187",
    "2066718740704596186",
    "2066718228810694913",
    "2066629554991427647",
    "2066539990088106389",
    "2066467618676953340",
    "2066784339472310422"
  ],
  "pending": {
    "james_trafford_newcastle_transfer": {
      "sources": [
        "David_Ornstein"
      ],
      "player": "James Trafford",
      "to_club": "Newcastle",
      "stype": "transfer",
      "last_seen": "2026-06-16T08:09:34.504171+00:00"
    }
  }
}